Powerset/__init__.py
Powerset-0.0.1.dist-info/LICENSE
Powerset-0.0.1.dist-info/METADATA
Powerset-0.0.1.dist-info/WHEEL
Powerset-0.0.1.dist-info/top_level.txt
Powerset-0.0.1.dist-info/RECORD
