Metadata-Version: 2.1
Name: Powerset
Version: 0.0.1
Summary: PowerSet is a set of 3 functions made in Python to work with lists as powerlists founded in mathematical powersets.
Home-page: https://github.com/MarcosRecio/PowerSet
Author: Marcos M. Recio
Author-email: marcosmanuelrecioperez@usal.es
License: UNKNOWN
Platform: UNKNOWN
Classifier: Programming Language :: Python :: 3
Classifier: License :: OSI Approved :: GNU General Public License v3 (GPLv3)
Classifier: Operating System :: OS Independent
Requires-Python: >=3.0
